{
  "type": "ADDED",
  "object": {
    "kind": "Pod",
    "apiVersion": "v1",

  "metadata": {
    "name": "Pod-customers-deployment#1",
    "namespace": "default",
    "uid": "Pod-customers-deployment#1",
    "resourceVersion": "19302",
    "creationTimestamp": "2022-01-26T14:02:05Z"
  },
  "spec": {
    "containers": [{
  "name": "customers",
  "resources": {
    "requests": {
      "cpu": "10"
    }
  }
}],
    "restartPolicy": "Always",
    "terminationGracePeriodSeconds": 30,
    "dnsPolicy": "ClusterFirst",
    "serviceAccountName": "default",
    "serviceAccount": "default",
    "securityContext": {
    },

    "affinity": {},
    "schedulerName": "my-scheduler",
    "tolerations": [
      {
        "key": "node.kubernetes.io/not-ready",
        "operator": "Exists",
        "effect": "NoExecute",
        "tolerationSeconds": 300
      },
      {
        "key": "node.kubernetes.io/unreachable",
        "operator": "Exists",
        "effect": "NoExecute",
        "tolerationSeconds": 300
      }
    ],
    "priority": 0,
    "enableServiceLinks": true,
    "preemptionPolicy": "PreemptLowerPriority"
  },
  "status": {
    "phase": "Pending",
    "qosClass": "BestEffort"
  }

  }
}
